dataclass_wizard/__init__.py
dataclass_wizard/__version__.py
dataclass_wizard/abstractions.py
dataclass_wizard/abstractions.pyi
dataclass_wizard/bases.py
dataclass_wizard/bases_meta.py
dataclass_wizard/bases_meta.pyi
dataclass_wizard/class_helper.py
dataclass_wizard/class_helper.pyi
dataclass_wizard/constants.py
dataclass_wizard/decorators.py
dataclass_wizard/dumpers.py
dataclass_wizard/enums.py
dataclass_wizard/errors.py
dataclass_wizard/errors.pyi
dataclass_wizard/lazy_imports.py
dataclass_wizard/loader_selection.py
dataclass_wizard/loaders.py
dataclass_wizard/log.py
dataclass_wizard/models.py
dataclass_wizard/models.pyi
dataclass_wizard/parsers.py
dataclass_wizard/property_wizard.py
dataclass_wizard/py.typed
dataclass_wizard/serial_json.py
dataclass_wizard/serial_json.pyi
dataclass_wizard/type_def.py
dataclass_wizard/wizard_mixins.py
dataclass_wizard/wizard_mixins.pyi
dataclass_wizard/environ/__init__.py
dataclass_wizard/environ/dumpers.py
dataclass_wizard/environ/loaders.py
dataclass_wizard/environ/lookups.py
dataclass_wizard/environ/lookups.pyi
dataclass_wizard/environ/wizard.py
dataclass_wizard/environ/wizard.pyi
dataclass_wizard/utils/__init__.py
dataclass_wizard/utils/dataclass_compat.py
dataclass_wizard/utils/dict_helper.py
dataclass_wizard/utils/function_builder.py
dataclass_wizard/utils/json_util.py
dataclass_wizard/utils/lazy_loader.py
dataclass_wizard/utils/object_path.py
dataclass_wizard/utils/object_path.pyi
dataclass_wizard/utils/string_conv.py
dataclass_wizard/utils/type_conv.py
dataclass_wizard/utils/typing_compat.py
dataclass_wizard/utils/wrappers.py
dataclass_wizard/v1/__init__.py
dataclass_wizard/v1/decorators.py
dataclass_wizard/v1/dumpers.py
dataclass_wizard/v1/enums.py
dataclass_wizard/v1/loaders.py
dataclass_wizard/v1/models.py
dataclass_wizard/v1/models.pyi
dataclass_wizard/v1/type_conv.py
dataclass_wizard/wizard_cli/__init__.py
dataclass_wizard/wizard_cli/cli.py
dataclass_wizard/wizard_cli/schema.py
dataclass_wizard-0.37.0.dist-info/licenses/LICENSE
dataclass_wizard-0.37.0.dist-info/METADATA
dataclass_wizard-0.37.0.dist-info/WHEEL
dataclass_wizard-0.37.0.dist-info/entry_points.txt
dataclass_wizard-0.37.0.dist-info/top_level.txt
dataclass_wizard-0.37.0.dist-info/RECORD
