Metadata-Version: 2.4
Name: dataclass-wizard
Version: 0.37.0
Summary: A wizard-like JSON serialization library for Python dataclasses
Author-email: Ritvik Nag <me@ritviknag.com>
License: Apache Software License 2.0
Project-URL: Discussions, https://github.com/rnag/dataclass-wizard/discussions
Project-URL: Changelog, https://dcw.ritviknag.com/en/latest/history.html
Project-URL: Source, https://github.com/rnag/dataclass-wizard
Project-URL: Download, https://pypi.org/project/dataclass-wizard
Project-URL: Documentation, https://dcw.ritviknag.com
Project-URL: Bug Tracker, https://github.com/rnag/dataclass-wizard/issues
Keywords: dataclasses,wizard,json,serialization,deserialization,dataclass serialization,type hints,performance,alias,python,env,dotenv,lightweight
Classifier: Development Status :: 5 - Production/Stable
Classifier: Intended Audience :: Developers
Classifier: License :: OSI Approved :: Apache Software License
Classifier: Natural Language :: English
Classifier: Programming Language :: Python :: 3 :: Only
Classifier: Programming Language :: Python :: 3
Classifier: Programming Language :: Python :: 3.9
Classifier: Programming Language :: Python :: 3.10
Classifier: Programming Language :: Python :: 3.11
Classifier: Programming Language :: Python :: 3.12
Classifier: Programming Language :: Python :: 3.13
Classifier: Programming Language :: Python :: 3.14
Classifier: Programming Language :: Python
Classifier: Typing :: Typed
Requires-Python: >=3.9
License-File: LICENSE
Requires-Dist: typing-extensions>=4.13.0; python_version <= "3.13"
Provides-Extra: dotenv
Requires-Dist: python-dotenv<2,>=1; extra == "dotenv"
Provides-Extra: timedelta
Requires-Dist: pytimeparse>=1.1.7; extra == "timedelta"
Provides-Extra: toml
Requires-Dist: tomli<3,>=2; python_version == "3.9" and extra == "toml"
Requires-Dist: tomli<3,>=2; python_version == "3.10" and extra == "toml"
Requires-Dist: tomli-w<2,>=1; extra == "toml"
Provides-Extra: yaml
Requires-Dist: PyYAML<7,>=6; extra == "yaml"
Provides-Extra: dev
Requires-Dist: flake8>=3; extra == "dev"
Requires-Dist: tox==4.23.2; extra == "dev"
Requires-Dist: pytimeparse==1.1.8; extra == "dev"
Requires-Dist: python-dotenv<2,>=1; extra == "dev"
Requires-Dist: tomli<3,>=2; python_version == "3.9" and extra == "dev"
Requires-Dist: tomli<3,>=2; python_version == "3.10" and extra == "dev"
Requires-Dist: tomli-w<2,>=1; extra == "dev"
Requires-Dist: coverage>=6.2; extra == "dev"
Requires-Dist: pip>=21.3.1; extra == "dev"
Requires-Dist: bump-my-version==1.2.5; extra == "dev"
Requires-Dist: wheel==0.45.1; extra == "dev"
Requires-Dist: watchdog[watchmedo]==6.0.0; extra == "dev"
Requires-Dist: Sphinx==7.4.7; python_version == "3.9" and extra == "dev"
Requires-Dist: Sphinx==8.1.3; python_version >= "3.10" and extra == "dev"
Requires-Dist: twine==6.0.1; extra == "dev"
Requires-Dist: dataclass-wizard[toml]; extra == "dev"
Provides-Extra: docs
Requires-Dist: sphinx-issues==5.0.0; extra == "docs"
Requires-Dist: sphinx-autodoc-typehints==2.5.0; python_version >= "3.10" and extra == "docs"
Requires-Dist: sphinx-copybutton==0.5.2; extra == "docs"
Requires-Dist: typing-extensions>=4.9.0; extra == "docs"
Provides-Extra: test
Requires-Dist: pytest==8.3.4; extra == "test"
Requires-Dist: pytest-mock>=3.6.1; extra == "test"
Requires-Dist: pytest-cov==6.0.0; extra == "test"
Provides-Extra: bench
Requires-Dist: matplotlib; extra == "bench"
Requires-Dist: pytest-benchmark[histogram]; extra == "bench"
Requires-Dist: dataclasses-json==0.6.7; extra == "bench"
Requires-Dist: jsons==1.6.3; extra == "bench"
Requires-Dist: dataclass-factory==2.16; extra == "bench"
Requires-Dist: dacite==1.8.1; extra == "bench"
Requires-Dist: mashumaro==3.15; extra == "bench"
Requires-Dist: pydantic==2.10.3; python_version < "3.14" and extra == "bench"
Requires-Dist: attrs==24.3.0; extra == "bench"
Provides-Extra: all
Requires-Dist: python-dotenv<2,>=1; extra == "all"
Requires-Dist: pytimeparse>=1.1.7; extra == "all"
Requires-Dist: tomli<3,>=2; python_version == "3.9" and extra == "all"
Requires-Dist: tomli<3,>=2; python_version == "3.10" and extra == "all"
Requires-Dist: tomli-w<2,>=1; extra == "all"
Requires-Dist: PyYAML<7,>=6; extra == "all"
Requires-Dist: flake8>=3; extra == "all"
Requires-Dist: tox==4.23.2; extra == "all"
Requires-Dist: pytimeparse==1.1.8; extra == "all"
Requires-Dist: coverage>=6.2; extra == "all"
Requires-Dist: bump-my-version==1.2.5; extra == "all"
Requires-Dist: wheel==0.45.1; extra == "all"
Requires-Dist: watchdog[watchmedo]==6.0.0; extra == "all"
Requires-Dist: Sphinx==7.4.7; python_version == "3.9" and extra == "all"
Requires-Dist: Sphinx==8.1.3; python_version >= "3.10" and extra == "all"
Requires-Dist: twine==6.0.1; extra == "all"
Requires-Dist: sphinx-issues==5.0.0; extra == "all"
Requires-Dist: sphinx-autodoc-typehints==2.5.0; python_version >= "3.10" and extra == "all"
Requires-Dist: sphinx-copybutton==0.5.2; extra == "all"
Requires-Dist: typing-extensions>=4.9.0; extra == "all"
Requires-Dist: pytest==8.3.4; extra == "all"
Requires-Dist: pytest-mock>=3.6.1; extra == "all"
Requires-Dist: pytest-cov==6.0.0; extra == "all"
Requires-Dist: matplotlib; extra == "all"
Requires-Dist: pytest-benchmark[histogram]; extra == "all"
Requires-Dist: dataclasses-json==0.6.7; extra == "all"
Requires-Dist: jsons==1.6.3; extra == "all"
Requires-Dist: dataclass-factory==2.16; extra == "all"
Requires-Dist: dacite==1.8.1; extra == "all"
Requires-Dist: mashumaro==3.15; extra == "all"
Requires-Dist: pydantic==2.10.3; python_version < "3.14" and extra == "all"
Requires-Dist: attrs==24.3.0; extra == "all"
Dynamic: license-file
